tushare_utils/__init__.py
tushare_utils-0.1.0.dist-info/METADATA
tushare_utils-0.1.0.dist-info/WHEEL
tushare_utils-0.1.0.dist-info/RECORD
