Metadata-Version: 2.4
Name: tushare-utils
Version: 0.1.0
Summary: Add your description here
License: MIT
Requires-Python: >=3.12
Requires-Dist: requests>=2.32.5
